window/__init__.py
window/viewport.py
window_viewport-0.0.1.dist-info/METADATA
window_viewport-0.0.1.dist-info/WHEEL
window_viewport-0.0.1.dist-info/top_level.txt
window_viewport-0.0.1.dist-info/RECORD
